{
    "id": 1,
    "materi": "Perbandingan Berbalik Nilai",
    "pertanyaan": "Alternatifa Project membangun sebuah gedung kantor baru. Diperkirakan akan selesai dalam waktu 12 bulan apabila mempekerjakan 20 orang. Ternyata pihak Alternatifa Project ingin pekerjaan lebih cepat selesai menjadi 8 bulan. Tambahan pekerja yang dibutuhkan agar gedung selesai dalam 8 bulan adalah...",
    "pilihan": [
      "8",
      "9",
      "10",
      "11",
      "12"
    ],
    "jawaban": "C",
    "pembahasan": "**Langkah 1: Menghitung Total Pekerja yang Dibutuhkan ($P_2$)**\n\nGunakan prinsip perbandingan berbalik nilai: $W_1 \\times P_1 = W_2 \\times P_2$\n\nDiketahui: $W_1 = 12$ bulan, $P_1 = 20$ orang, $W_2 = 8$ bulan.\n\n$$12 \\times 20 = 8 \\times P_2$$\n$$240 = 8 \\times P_2$$\n$$P_2 = \\frac{240}{8}$$\n$$P_2 = 30 \\text{ orang}$$\n\n**Langkah 2: Menghitung Tambahan Pekerja**\n\n$$\\text{Tambahan Pekerja} = P_2 - P_1$$\n$$\\text{Tambahan Pekerja} = 30 - 20$$\n$$\\text{Tambahan Pekerja} = 10 \\text{ orang}$$"
  }
