[
  {
    "id": 1,
    "pertanyaan": "Jika $a = \\frac{1}{2}$, $b = 0.75$, dan $c = 0.6$, urutan bilangan dari yang terkecil ke terbesar adalah...",
    "pilihan": ["a, b, c", "a, c, b", "b, a, c", "c, a, b", "c, b, a"],
    "jawaban": "B",
    "pembahasan": "Ubah semua bilangan ke bentuk desimal untuk memudahkan perbandingan:\n$a = \\frac{1}{2} = 0.5$\n$b = 0.75$\n$c = 0.6$\n\nUrutan dari yang terkecil ke terbesar adalah: 0.5, 0.6, 0.75. Jadi, **a, c, b**."
  },
  {
    "id": 2,
    "pertanyaan": "Sebuah mobil menghabiskan 1 liter bensin untuk menempuh jarak 12 km. Jika mobil tersebut ingin menempuh jarak 180 km, berapa liter bensin yang dibutuhkan?",
    "pilihan": ["12 liter", "15 liter", "18 liter", "20 liter", "24 liter"],
    "jawaban": "B",
    "pembahasan": "Untuk menempuh 180 km, jumlah bensin yang dibutuhkan adalah:\nBensin = Jarak yang ditempuh / Jarak per liter\nBensin = 180 km / 12 km/liter\nBensin = **15 liter**."
  },
  {
    "id": 3,
    "pertanyaan": "Jika $P$ adalah banyaknya bilangan prima antara 10 dan 20, dan $Q$ adalah banyaknya bilangan ganjil antara 10 dan 20, maka hubungan yang tepat antara $P$ dan $Q$ adalah...",
    "pilihan": ["P > Q", "P < Q", "P = Q", "P = 2Q", "Tidak dapat ditentukan"],
    "jawaban": "B",
    "pembahasan": "Bilangan prima antara 10 dan 20 adalah: 11, 13, 17, 19. Jadi, $P = 4$.\nBilangan ganjil antara 10 dan 20 adalah: 11, 13, 15, 17, 19. Jadi, $Q = 5$.\nKarena $P = 4$ dan $Q = 5$, maka $P < Q$."
  },
  {
    "id": 4,
    "pertanyaan": "Sebuah segitiga memiliki alas 10 cm dan tinggi 8 cm. Berapakah luas segitiga tersebut?",
    "pilihan": ["20 cm²", "30 cm²", "40 cm²", "50 cm²", "60 cm²"],
    "jawaban": "C",
    "pembahasan": "Rumus luas segitiga adalah $\\frac{1}{2} \\times alas \\times tinggi$.\nLuas = $\\frac{1}{2} \\times 10 \\times 8$\nLuas = $5 \\times 8$\nLuas = **40 cm²**."
  },
  {
    "id": 5,
    "pertanyaan": "Harga sebuah televisi naik 20% dari harga semula. Jika harga televisi sekarang adalah Rp 3.600.000,00, berapa harga televisi semula?",
    "pilihan": ["Rp 2.880.000,00", "Rp 3.000.000,00", "Rp 3.200.000,00", "Rp 3.400.000,00", "Rp 3.500.000,00"],
    "jawaban": "B",
    "pembahasan": "Misalkan harga semula = H.\nHarga sekarang = H + 20% H = 120% H = 1.2 H.\nDiketahui harga sekarang = Rp 3.600.000,00.\n$1.2 \\times H = 3.600.000$\n$H = 3.600.000 / 1.2$\n$H = 3.600.000 \\times (10/12)$\n$H = 3.000.000$\nJadi, harga televisi semula adalah **Rp 3.000.000,00**."
  },
  {
    "id": 6,
    "pertanyaan": "Jika $a + b = 8$ dan $a^2 - b^2 = 32$, maka nilai dari $a - b$ adalah...",
    "pilihan": ["2", "4", "6", "8", "10"],
    "jawaban": "B",
    "pembahasan": "Kita tahu bahwa $a^2 - b^2$ dapat difaktorkan menjadi $(a - b)(a + b)$.\nDiketahui $a^2 - b^2 = 32$ dan $a + b = 8$.\nSubstitusikan nilai-nilai tersebut ke dalam persamaan faktorisasi:\n$(a - b)(a + b) = 32$\n$(a - b) \\times 8 = 32$\n$a - b = 32 / 8$\n$a - b = \\textbf{4}$."
  },
  {
    "id": 7,
    "pertanyaan": "Sebuah bak mandi berbentuk balok memiliki panjang 150 cm, lebar 100 cm, dan tinggi 80 cm. Jika bak tersebut terisi air 3/4 bagian, berapa volume air dalam bak tersebut (dalam liter)?",
    "pilihan": ["90 liter", "900 liter", "9.000 liter", "90.000 liter", "900.000 liter"],
    "jawaban": "B",
    "pembahasan": "Volume total bak mandi = Panjang $\\times$ Lebar $\\times$ Tinggi\nVolume total = 150 cm $\\times$ 100 cm $\\times$ 80 cm = 1.200.000 cm³.\nIngat bahwa 1 liter = 1.000 cm³.\nVolume total dalam liter = 1.200.000 / 1.000 = 1.200 liter.\nAir terisi 3/4 bagian dari volume total:\nVolume air = $\\frac{3}{4} \\times 1.200$ liter\nVolume air = $3 \\times 300$ liter\nVolume air = **900 liter**."
  },
  {
    "id": 8,
    "pertanyaan": "Seorang pelari menempuh jarak 100 meter dalam waktu 12 detik. Berapa kecepatan rata-rata pelari tersebut dalam km/jam?",
    "pilihan": ["25 km/jam", "30 km/jam", "35 km/jam", "40 km/jam", "45 km/jam"],
    "jawaban": "D",
    "pembahasan": "Kecepatan = Jarak / Waktu\nKecepatan = 100 meter / 12 detik.\n\nKonversi satuan:\n1 km = 1000 meter $\\implies$ 1 meter = 1/1000 km\n1 jam = 3600 detik $\\implies$ 1 detik = 1/3600 jam\n\nKecepatan = (100 / 1000) km / (12 / 3600) jam\nKecepatan = (1/10) km / (1/300) jam\nKecepatan = (1/10) $\\times$ 300 km/jam\nKecepatan = **30 km/jam**."
  },
  {
    "id": 9,
    "pertanyaan": "Jika $x$ adalah bilangan bulat positif yang habis dibagi 3 dan 5, dan $x < 50$, berapa nilai $x$ yang paling besar?",
    "pilihan": ["15", "30", "45", "48", "49"],
    "jawaban": "C",
    "pembahasan": "Jika $x$ habis dibagi 3 dan 5, maka $x$ adalah kelipatan persekutuan terkecil (KPK) dari 3 dan 5.\nKPK(3, 5) = 15.\nJadi, $x$ adalah kelipatan dari 15.\nKelipatan 15 yang kurang dari 50 adalah: 15, 30, 45.\nNilai $x$ yang paling besar adalah **45**."
  },
  {
    "id": 10,
    "pertanyaan": "Dalam sebuah antrean, posisi Rudi adalah urutan ke-7 dari depan dan urutan ke-15 dari belakang. Berapa jumlah orang dalam antrean tersebut?",
    "pilihan": ["20", "21", "22", "23", "24"],
    "jawaban": "B",
    "pembahasan": "Jumlah orang dalam antrean = (Posisi dari depan) + (Posisi dari belakang) - 1\nDikurangi 1 karena Rudi dihitung dua kali (dari depan dan dari belakang).\nJumlah orang = 7 + 15 - 1\nJumlah orang = 22 - 1\nJumlah orang = **21**."
  }
]

